canonada/__init__.py
canonada/_config.py
canonada/_logger.py
canonada/_version.py
canonada/cli.py
canonada/_utils/progressbar.py
canonada/catalog/__init__.py
canonada/catalog/_core.py
canonada/catalog/_datahandlers.py
canonada/exceptions/__init__.py
canonada/exceptions/_exceptions.py
canonada/pipeline/__init__.py
canonada/pipeline/_core.py
canonada/system/__init__.py
canonada/system/_core.py
canonada/templates/canonada.toml
canonada/templates/gitignore
canonada/templates/config/catalog.toml
canonada/templates/config/credentials.toml
canonada/templates/config/parameters.toml
canonada/templates/datahandlers/__init__.py
canonada/templates/pipelines/__init__.py
canonada/templates/pipelines/nodes/__init__.py
canonada/templates/systems/__init__.py
canonada-0.6.5.dist-info/licenses/LICENSE
canonada-0.6.5.dist-info/METADATA
canonada-0.6.5.dist-info/WHEEL
canonada-0.6.5.dist-info/entry_points.txt
canonada-0.6.5.dist-info/top_level.txt
canonada-0.6.5.dist-info/RECORD
