Metadata-Version: 2.4
Name: canonada
Version: 0.6.5
Summary: Canonada is a data science framework that helps you build production-ready streaming pipelines for data processing in Python.
Author-email: Ricard Lado <ricard@lado.one>
License: MIT
Project-URL: Homepage, https://github.com/RLado/Canonada
Project-URL: Issues, https://github.com/RLado/Canonada/issues
Keywords: data science,streaming,pipeline,dataflow,canonada
Classifier: Programming Language :: Python :: 3
Classifier: License :: OSI Approved :: MIT License
Classifier: Operating System :: OS Independent
Classifier: Topic :: Software Development
Classifier: Topic :: Scientific/Engineering :: Information Analysis
Classifier: Topic :: Scientific/Engineering :: Artificial Intelligence
Requires-Python: >=3.11
License-File: LICENSE
Requires-Dist: graphviz==0.20.3
Provides-Extra: dev
Requires-Dist: build>=1.2.2; extra == "dev"
Requires-Dist: coverage>=7.0.0; extra == "dev"
Requires-Dist: setuptools>=61.0; extra == "dev"
Requires-Dist: twine>=6.1.0; extra == "dev"
Requires-Dist: mypy>=1.15.0; extra == "dev"
Dynamic: license-file
